README.txt
setup.cfg
setup.py
cs/__init__.py
cs.donedukia.egg-info/PKG-INFO
cs.donedukia.egg-info/SOURCES.txt
cs.donedukia.egg-info/dependency_links.txt
cs.donedukia.egg-info/entry_points.txt
cs.donedukia.egg-info/namespace_packages.txt
cs.donedukia.egg-info/not-zip-safe
cs.donedukia.egg-info/requires.txt
cs.donedukia.egg-info/top_level.txt
cs/donedukia/__init__.py
cs/donedukia/config.py
cs/donedukia/configure.zcml
cs/donedukia/interfaces.py
cs/donedukia/rebuild_i18n.sh
cs/donedukia/tests.py
cs/donedukia/Extensions/Install.py
cs/donedukia/Extensions/__init__.py
cs/donedukia/browser/__init__.py
cs/donedukia/browser/configure.zcml
cs/donedukia/browser/don_edukia.gif
cs/donedukia/browser/donedukiaview.pt
cs/donedukia/browser/donedukiaview.py
cs/donedukia/browser/folder_listing_donedukia.pt
cs/donedukia/content/__init__.py
cs/donedukia/content/configure.zcml
cs/donedukia/content/donedukia.py
cs/donedukia/locales/cs.donedukia-manual.pot
cs/donedukia/locales/cs.donedukia.pot
cs/donedukia/locales/en/LC_MESSAGES/cs.donedukia.po
cs/donedukia/locales/es/LC_MESSAGES/cs.donedukia.po
cs/donedukia/locales/eu/LC_MESSAGES/cs.donedukia.po
cs/donedukia/profiles/default/factorytool.xml
cs/donedukia/profiles/default/metadata.xml
cs/donedukia/profiles/default/rolemap.xml
cs/donedukia/profiles/default/tinymce.xml
cs/donedukia/profiles/default/types.xml
cs/donedukia/profiles/default/types/DonEdukia.xml
cs/donedukia/tests/__init__.py
docs/HISTORY.txt
docs/INSTALL.txt
docs/LICENSE.GPL
docs/LICENSE.txt