Metadata-Version: 1.1
Name: cs.donedukia
Version: 2.1.1
Summary: Folderish pages to simplify plone page-folder story
Home-page: http://github.com/codesyntax/cs.donedukia
Author: Mikel Larreategi
Author-email: mlarreategi@codesyntax.com
License: GPL
Keywords: plone page folderish
Platform: UNKNOWN
Classifier: Framework :: Plone
Classifier: Programming Language :: Python
Classifier: Topic :: Software Development :: Libraries :: Python Modules
